axonflow/__init__.py
axonflow/client.py
axonflow/code_governance.py
axonflow/exceptions.py
axonflow/execution.py
axonflow/masfeat.py
axonflow/policies.py
axonflow/py.typed
axonflow/types.py
axonflow/workflow.py
axonflow/adapters/__init__.py
axonflow/adapters/langgraph.py
axonflow/interceptors/__init__.py
axonflow/interceptors/anthropic.py
axonflow/interceptors/base.py
axonflow/interceptors/bedrock.py
axonflow/interceptors/gemini.py
axonflow/interceptors/ollama.py
axonflow/interceptors/openai.py
axonflow/utils/__init__.py
axonflow/utils/cache.py
axonflow/utils/logging.py
axonflow/utils/retry.py
axonflow-1.7.1.dist-info/licenses/LICENSE
axonflow-1.7.1.dist-info/METADATA
axonflow-1.7.1.dist-info/WHEEL
axonflow-1.7.1.dist-info/top_level.txt
axonflow-1.7.1.dist-info/RECORD
