Metadata-Version: 2.4
Name: axonflow
Version: 1.7.1
Summary: AxonFlow Python SDK - Enterprise AI Governance in 3 Lines of Code
Author-email: AxonFlow <dev@getaxonflow.com>
Maintainer-email: AxonFlow <dev@getaxonflow.com>
License: MIT
Project-URL: Homepage, https://getaxonflow.com
Project-URL: Documentation, https://docs.getaxonflow.com/sdk/python-getting-started
Project-URL: Repository, https://github.com/getaxonflow/axonflow-sdk-python
Project-URL: Changelog, https://github.com/getaxonflow/axonflow-sdk-python/blob/main/CHANGELOG.md
Project-URL: Issues, https://github.com/getaxonflow/axonflow-sdk-python/issues
Keywords: ai,governance,llm,openai,anthropic,bedrock,policy,compliance,enterprise,mcp,multi-agent
Classifier: Development Status :: 5 - Production/Stable
Classifier: Intended Audience :: Developers
Classifier: License :: OSI Approved :: MIT License
Classifier: Operating System :: OS Independent
Classifier: Programming Language :: Python :: 3
Classifier: Programming Language :: Python :: 3.9
Classifier: Programming Language :: Python :: 3.10
Classifier: Programming Language :: Python :: 3.11
Classifier: Programming Language :: Python :: 3.12
Classifier: Topic :: Software Development :: Libraries :: Python Modules
Classifier: Topic :: Scientific/Engineering :: Artificial Intelligence
Classifier: Typing :: Typed
Requires-Python: >=3.9
License-File: LICENSE
Requires-Dist: httpx>=0.25.0
Requires-Dist: pydantic>=2.0.0
Requires-Dist: tenacity>=8.0.0
Requires-Dist: structlog>=23.0.0
Requires-Dist: cachetools>=5.0.0
Requires-Dist: eval_type_backport>=0.2.0; python_version < "3.10"
Provides-Extra: dev
Requires-Dist: pytest>=7.0.0; extra == "dev"
Requires-Dist: pytest-asyncio>=0.21.0; extra == "dev"
Requires-Dist: pytest-cov>=4.0.0; extra == "dev"
Requires-Dist: pytest-httpx>=0.22.0; extra == "dev"
Requires-Dist: mypy>=1.5.0; extra == "dev"
Requires-Dist: types-cachetools>=5.0.0; extra == "dev"
Requires-Dist: ruff>=0.1.0; extra == "dev"
Requires-Dist: black>=23.0.0; extra == "dev"
Requires-Dist: isort>=5.12.0; extra == "dev"
Requires-Dist: pre-commit>=3.0.0; extra == "dev"
Provides-Extra: docs
Requires-Dist: sphinx>=7.0.0; extra == "docs"
Requires-Dist: sphinx-rtd-theme>=1.3.0; extra == "docs"
Requires-Dist: sphinx-autodoc-typehints>=1.24.0; extra == "docs"
Requires-Dist: myst-parser>=2.0.0; extra == "docs"
Provides-Extra: openai
Requires-Dist: openai>=1.0.0; extra == "openai"
Provides-Extra: anthropic
Requires-Dist: anthropic>=0.18.0; extra == "anthropic"
Provides-Extra: all
Requires-Dist: openai>=1.0.0; extra == "all"
Requires-Dist: anthropic>=0.18.0; extra == "all"
Dynamic: license-file
